{"skeleton":{"hash":"KxS1wHZNf5N3PcLhDRIc6nuXWSs","spine":"3.8.99","x":-91,"y":-76.5,"width":182,"height":153,"fps":60,"images":"./img/","audio":""},"bones":[{"name":"root"},{"name":"Scatter_B","parent":"root"},{"name":"Scatter_B_1_Text_Actor","parent":"Scatter_B"},{"name":"Scatter_B_1_Text","parent":"Scatter_B_1_Text_Actor"},{"name":"Scatter_B_2_BG","parent":"Scatter_B"},{"name":"Scatter_B_3_Pin","parent":"Scatter_B"},{"name":"Scatter_B_4_Deco","parent":"Scatter_B"},{"name":"Scatter_B_5_Frame","parent":"Scatter_B"},{"name":"Scatter_B_6_Gear","parent":"Scatter_B"},{"name":"Scatter_B_7_Wheel","parent":"Scatter_B"},{"name":"Scatter_B_8_Cap1","parent":"Scatter_B"},{"name":"Scatter_B_9_Cap2","parent":"Scatter_B"},{"name":"Scatter_B_1_Text_Ref","parent":"Scatter_B_1_Text_Actor"},{"name":"FX_Group","parent":"root"},{"name":"FX_1","parent":"FX_Group"},{"name":"FX_2","parent":"FX_Group"},{"name":"FX_3","parent":"FX_Group"},{"name":"FX4","parent":"Scatter_B_3_Pin","y":68.8,"scaleX":0.7,"scaleY":0.7},{"name":"FX_6","parent":"FX_Group"},{"name":"FX_5","parent":"FX_Group"}],"slots":[{"name":"Scatter_B_2_BG","bone":"Scatter_B_2_BG","attachment":"Scatter_B_2"},{"name":"Scatter_B_5_Frame","bone":"Scatter_B_5_Frame","attachment":"Scatter_B_5"},{"name":"Scatter_B_5_Frame2","bone":"Scatter_B_5_Frame"},{"name":"Scatter_B_6_Gear","bone":"Scatter_B_6_Gear","attachment":"Scatter_B_6"},{"name":"Scatter_B_6_Gear2","bone":"Scatter_B_6_Gear"},{"name":"Scatter_B_7_Wheel","bone":"Scatter_B_7_Wheel","attachment":"Scatter_B_7"},{"name":"Scatter_B_7_Wheel2","bone":"Scatter_B_7_Wheel"},{"name":"Scatter_B_7_Wheel3","bone":"Scatter_B_7_Wheel"},{"name":"Scatter_B_3-2","bone":"Scatter_B_3_Pin"},{"name":"Ptcl_02","bone":"FX_1"},{"name":"Ptcl_06","bone":"FX_2"},{"name":"FX5","bone":"FX_5","blend":"additive"},{"name":"FX6","bone":"FX_6"},{"name":"Scatter_B_4_Deco","bone":"Scatter_B_4_Deco","attachment":"Scatter_B_4"},{"name":"Scatter_B_4_Deco2","bone":"Scatter_B_4_Deco"},{"name":"Scatter_B_3_Pin","bone":"Scatter_B_3_Pin","attachment":"Scatter_B_3"},{"name":"Scatter_B_8_Cap1","bone":"Scatter_B_8_Cap1","attachment":"Scatter_B_8"},{"name":"Scatter_B_8_Cap2","bone":"Scatter_B_8_Cap1"},{"name":"Scatter_B_9_Cap2","bone":"Scatter_B_9_Cap2","attachment":"Scatter_B_9"},{"name":"Scatter_B_9_Cap3","bone":"Scatter_B_9_Cap2"},{"name":"Scatter_B_1_Text","bone":"Scatter_B_1_Text","attachment":"Scatter_B_1"},{"name":"Scatter_Text_Ref","bone":"Scatter_B_1_Text_Ref"},{"name":"Scatter_B_1_Text2","bone":"Scatter_B_1_Text"},{"name":"Spark_2","bone":"FX_3","blend":"additive"},{"name":"FX4","bone":"FX4","blend":"additive"}],"skins":[{"name":"default","attachments":{"FX4":{"FX4":{"path":"Scatter/FX4","width":485,"height":303}},"FX5":{"FX5":{"path":"Scatter/FX5","width":194,"height":194}},"FX6":{"FX6":{"path":"Scatter/FX6","width":137,"height":137}},"Ptcl_02":{"Ptcl_02":{"path":"Scatter/Ptcl_02","scaleX":0.7,"scaleY":0.7,"width":485,"height":485}},"Ptcl_06":{"Ptcl_06":{"path":"Scatter/Ptcl_06","width":248,"height":248}},"Scatter_B_1_Text":{"Scatter_B_1":{"path":"Scatter/Scatter_B_1","width":182,"height":153}},"Scatter_B_1_Text2":{"Scatter_A_1-2":{"path":"Scatter/Scatter_A_1-2","width":182,"height":153}},"Scatter_B_2_BG":{"Scatter_B_2":{"path":"Scatter/Scatter_B_2","width":182,"height":153}},"Scatter_B_3-2":{"Scatter_B_3-2":{"path":"Scatter/Scatter_B_3-2","width":182,"height":153}},"Scatter_B_3_Pin":{"Scatter_B_3":{"path":"Scatter/Scatter_B_3","width":182,"height":153}},"Scatter_B_4_Deco":{"Scatter_B_4":{"path":"Scatter/Scatter_B_4","width":182,"height":153}},"Scatter_B_4_Deco2":{"Scatter_B_4-2":{"path":"Scatter/Scatter_B_4-2","width":182,"height":153}},"Scatter_B_5_Frame":{"Scatter_B_5":{"path":"Scatter/Scatter_B_5","width":182,"height":153}},"Scatter_B_5_Frame2":{"Scatter_B_5-2":{"path":"Scatter/Scatter_B_5-2","width":182,"height":153}},"Scatter_B_6_Gear":{"Scatter_B_6":{"path":"Scatter/Scatter_B_6","width":182,"height":153}},"Scatter_B_6_Gear2":{"Scatter_B_6-2":{"path":"Scatter/Scatter_B_6-2","width":182,"height":153}},"Scatter_B_7_Wheel":{"Scatter_B_7":{"path":"Scatter/Scatter_B_7","width":152,"height":152}},"Scatter_B_7_Wheel2":{"Scatter_B_7-2":{"path":"Scatter/Scatter_B_7-2","width":152,"height":152}},"Scatter_B_7_Wheel3":{"Scatter_B_7-3":{"path":"Scatter/Scatter_B_7-3","width":152,"height":152}},"Scatter_B_8_Cap1":{"Scatter_B_8":{"path":"Scatter/Scatter_B_8","width":182,"height":153}},"Scatter_B_8_Cap2":{"Scatter_B_8-2":{"path":"Scatter/Scatter_B_8-2","width":182,"height":153}},"Scatter_B_9_Cap2":{"Scatter_B_9":{"path":"Scatter/Scatter_B_9","width":182,"height":153}},"Scatter_B_9_Cap3":{"Scatter_B_9-2":{"path":"Scatter/Scatter_B_9-2","width":182,"height":153}},"Scatter_Text_Ref":{"Scatter_Text_Ref_00001":{"path":"Scatter/Scatter_Text_Ref_00001","width":182,"height":153},"Scatter_Text_Ref_00002":{"path":"Scatter/Scatter_Text_Ref_00002","width":182,"height":153},"Scatter_Text_Ref_00003":{"path":"Scatter/Scatter_Text_Ref_00003","width":182,"height":153},"Scatter_Text_Ref_00004":{"path":"Scatter/Scatter_Text_Ref_00004","width":182,"height":153},"Scatter_Text_Ref_00005":{"path":"Scatter/Scatter_Text_Ref_00005","width":182,"height":153},"Scatter_Text_Ref_00006":{"path":"Scatter/Scatter_Text_Ref_00006","width":182,"height":153},"Scatter_Text_Ref_00007":{"path":"Scatter/Scatter_Text_Ref_00007","width":182,"height":153},"Scatter_Text_Ref_00008":{"path":"Scatter/Scatter_Text_Ref_00008","width":182,"height":153},"Scatter_Text_Ref_00009":{"path":"Scatter/Scatter_Text_Ref_00009","width":182,"height":153},"Scatter_Text_Ref_00010":{"path":"Scatter/Scatter_Text_Ref_00010","width":182,"height":153},"Scatter_Text_Ref_00011":{"path":"Scatter/Scatter_Text_Ref_00011","width":182,"height":153},"Scatter_Text_Ref_00012":{"path":"Scatter/Scatter_Text_Ref_00012","width":182,"height":153}},"Spark_2":{"Spark_2":{"path":"Scatter/Spark_2","width":243,"height":243}}}}],"animations":{"Idle":{},"NearWin":{"slots":{"FX5":{"color":[{"color":"ffffff00","curve":0.25,"c3":0.75},{"time":0.1667,"color":"ffffffff","curve":0.25,"c3":0.75},{"time":0.3333,"color":"ffffff00","curve":0.25,"c3":0.75},{"time":0.5,"color":"ffffffff","curve":0.25,"c3":0.75},{"time":0.6667,"color":"ffffff00","curve":0.25,"c3":0.75},{"time":0.8333,"color":"ffffffff","curve":0.25,"c3":0.75},{"time":1,"color":"ffffff00"}],"attachment":[{"name":"FX5"}]},"FX6":{"color":[{"color":"ffffff00","curve":0.25,"c3":0.75},{"time":0.1667,"color":"ffffffff","curve":0.25,"c3":0.75},{"time":0.3333,"color":"ffffff00","curve":0.25,"c3":0.75},{"time":0.5,"color":"ffffffff","curve":0.25,"c3":0.75},{"time":0.6667,"color":"ffffff00","curve":0.25,"c3":0.75},{"time":0.8333,"color":"ffffffff","curve":0.25,"c3":0.75},{"time":1,"color":"ffffff00"}],"attachment":[{"name":"FX6"}]},"Scatter_Text_Ref":{"attachment":[{"time":0.0833,"name":"Scatter_Text_Ref_00001"},{"time":0.1667,"name":"Scatter_Text_Ref_00002"},{"time":0.25,"name":"Scatter_Text_Ref_00003"},{"time":0.3333,"name":"Scatter_Text_Ref_00004"},{"time":0.4167,"name":"Scatter_Text_Ref_00005"},{"time":0.5,"name":"Scatter_Text_Ref_00006"},{"time":0.5833,"name":"Scatter_Text_Ref_00007"},{"time":0.6667,"name":"Scatter_Text_Ref_00008"},{"time":0.75,"name":"Scatter_Text_Ref_00009"},{"time":0.8333,"name":"Scatter_Text_Ref_00010"},{"time":0.9167,"name":"Scatter_Text_Ref_00011"},{"time":1,"name":"Scatter_Text_Ref_00012"}]}},"bones":{"FX_5":{"rotate":[{},{"time":0.5,"angle":180},{"time":1}],"scale":[{"x":0.85,"y":0.85},{"time":0.5,"x":0.9,"y":0.9},{"time":1,"x":0.85,"y":0.85}]},"FX_6":{"rotate":[{},{"time":0.5,"angle":180},{"time":1}],"scale":[{},{"time":0.5,"x":1.1,"y":1.1},{"time":1}]},"Scatter_B_1_Text_Ref":{"translate":[{"y":45}]},"Scatter_B_7_Wheel":{"rotate":[{},{"time":0.25,"angle":180},{"time":0.5},{"time":0.75,"angle":180},{"time":1}],"scale":[{"curve":0.25,"c3":0.75},{"time":0.5,"x":1.1,"y":1.1,"curve":0.25,"c3":0.75},{"time":1}]},"Scatter_B_1_Text":{"translate":[{"y":45}]},"Scatter_B_1_Text_Actor":{"translate":[{"y":-45}],"scale":[{"curve":0.25,"c3":0.75},{"time":0.3333,"x":1.15,"curve":0.25,"c3":0.75},{"time":0.6667,"y":1.15,"curve":0.25,"c3":0.75},{"time":1}]},"Scatter_B_3_Pin":{"translate":[{"curve":0.25,"c3":0},{"time":0.5,"y":10,"curve":1,"c3":0.75},{"time":0.5833,"y":-7},{"time":0.6667,"y":3},{"time":0.75}]},"Scatter_B_4_Deco":{"scale":[{"time":0.0833,"curve":0.25,"c3":0},{"time":0.6667,"x":1.1,"y":1.1,"curve":0.25,"c3":0.75},{"time":0.75,"x":0.95,"y":0.95,"curve":0.25,"c3":0.75},{"time":0.8333,"x":1.02,"y":1.05,"curve":0.25,"c3":0.75},{"time":0.9167}]},"Scatter_B_6_Gear":{"scale":[{"curve":0.25,"c3":0.75},{"time":0.5,"x":1.1,"y":1.1,"curve":0.25,"c3":0.75},{"time":1}]},"Scatter_B_5_Frame":{"scale":[{"curve":0.25,"c3":0.75},{"time":0.5,"x":1.1,"y":1.1,"curve":0.25,"c3":0.75},{"time":1}]},"Scatter_B_8_Cap1":{"scale":[{},{"time":0.5,"x":1.1,"y":1.1},{"time":1}]},"Scatter_B_9_Cap2":{"scale":[{},{"time":0.5,"x":1.05,"y":1.05},{"time":1}]}}},"Stop":{"slots":{"FX4":{"color":[{"time":0.1667,"color":"ffffffff","curve":0.25,"c3":0.75},{"time":0.3333,"color":"ffffff00"}],"attachment":[{"name":"FX4"}]},"Scatter_B_1_Text2":{"color":[{"color":"ffffff00"},{"time":0.05,"color":"ffffffff"},{"time":0.1,"color":"ffffff00"}],"attachment":[{"name":"Scatter_A_1-2"}]},"Scatter_B_3-2":{"color":[{"time":0.0833,"color":"ffffff00","curve":0.25,"c3":0.75},{"time":0.1667,"color":"ffffffff","curve":0.25,"c3":0.75},{"time":0.25,"color":"ffffff00"}],"attachment":[{"time":0.0833,"name":"Scatter_B_3-2"}]},"Scatter_B_4_Deco2":{"color":[{"time":0.0833,"color":"ffffff00","curve":0.25,"c3":0.75},{"time":0.1667,"color":"ffffffff","curve":0.25,"c3":0.75},{"time":0.25,"color":"ffffff00"}],"attachment":[{"time":0.0833,"name":"Scatter_B_4-2"}]},"Scatter_B_7_Wheel2":{"color":[{"color":"ffffff00","curve":1,"c3":0.75},{"time":0.1667,"color":"ffffffff","curve":0.25,"c3":0},{"time":0.3333,"color":"ffffff00"}],"attachment":[{"name":"Scatter_B_7-2"}]},"Scatter_B_7_Wheel3":{"color":[{"color":"ffffff00","curve":1,"c3":0.75},{"time":0.1667,"color":"ffffffff","curve":0.25,"c3":0},{"time":0.3333,"color":"ffffff00"}]},"Scatter_Text_Ref":{"attachment":[{"name":"Scatter_Text_Ref_00001"},{"time":0.0333,"name":"Scatter_Text_Ref_00002"},{"time":0.0667,"name":"Scatter_Text_Ref_00003"},{"time":0.1,"name":"Scatter_Text_Ref_00004"},{"time":0.1333,"name":"Scatter_Text_Ref_00005"},{"time":0.1667,"name":"Scatter_Text_Ref_00006"},{"time":0.2,"name":"Scatter_Text_Ref_00007"},{"time":0.2333,"name":"Scatter_Text_Ref_00008"},{"time":0.2667,"name":"Scatter_Text_Ref_00009"},{"time":0.3,"name":"Scatter_Text_Ref_00010"},{"time":0.3333,"name":"Scatter_Text_Ref_00011"},{"time":0.3667,"name":"Scatter_Text_Ref_00012"},{"time":0.4,"name":null}]}},"bones":{"FX4":{"scale":[{"x":0,"y":0,"curve":0.25,"c3":0},{"time":0.3333}]},"Scatter_B_1_Text":{"translate":[{"y":45}]},"Scatter_B_3_Pin":{"translate":[{"time":0.05,"curve":1,"c3":0.75},{"time":0.1333,"y":11,"curve":0.25,"c3":0.75},{"time":0.2167,"y":8.8,"curve":0.25,"c3":0.75},{"time":0.3,"y":9,"curve":0.25,"c3":0.75},{"time":0.5}]},"Scatter_B_4_Deco":{"scale":[{"time":0.0667,"curve":1,"c3":0.75},{"time":0.15,"x":1.1,"y":1.1,"curve":0.25,"c3":0.75},{"time":0.2333,"x":1.07,"y":1.07,"curve":0.25,"c3":0.75},{"time":0.3167,"x":1.08,"y":1.08,"curve":0.622,"c2":0.43,"c3":0.496},{"time":0.5}]},"Scatter_B_7_Wheel":{"scale":[{"time":0.1,"curve":0.25,"c3":0.75},{"time":0.1833,"x":1.05,"y":1.05,"curve":0.307,"c3":0.642,"c4":0.35},{"time":0.2667,"x":1.03,"y":1.03,"curve":0.315,"c2":0.24,"c3":0.65,"c4":0.58},{"time":0.35,"x":1.04,"y":1.04,"curve":0.315,"c2":0.27,"c3":0.757},{"time":0.5}]},"Scatter_B_1_Text_Ref":{"translate":[{"y":45}]},"Scatter_B_1_Text_Actor":{"translate":[{"y":-45}],"scale":[{"curve":0.25,"c3":0.75},{"time":0.0833,"x":1.2,"y":1.2,"curve":0.25,"c3":0.75},{"time":0.1667,"x":1.1,"y":1.1,"curve":0.25,"c3":0},{"time":0.5}]},"Scatter_B_6_Gear":{"scale":[{"time":0.05,"curve":0.25,"c3":0.75},{"time":0.1333,"x":1.05,"y":1.05,"curve":0.307,"c3":0.642,"c4":0.35},{"time":0.2167,"x":1.03,"y":1.03,"curve":0.315,"c2":0.24,"c3":0.65,"c4":0.58},{"time":0.3,"x":1.04,"y":1.04,"curve":0.315,"c2":0.27,"c3":0.757},{"time":0.5}]},"Scatter_B_5_Frame":{"scale":[{"curve":0.25,"c3":0.75},{"time":0.0833,"x":1.05,"y":1.05,"curve":0.307,"c3":0.642,"c4":0.35},{"time":0.1667,"x":1.03,"y":1.03,"curve":0.315,"c2":0.24,"c3":0.65,"c4":0.58},{"time":0.25,"x":1.04,"y":1.04,"curve":0.315,"c2":0.27,"c3":0.757},{"time":0.5}]},"Scatter_B_8_Cap1":{"scale":[{"curve":0.25,"c3":0.75},{"time":0.0833,"x":1.05,"y":1.05,"curve":0.307,"c3":0.642,"c4":0.35},{"time":0.1667,"x":1.03,"y":1.03,"curve":0.315,"c2":0.24,"c3":0.65,"c4":0.58},{"time":0.25,"x":1.04,"y":1.04,"curve":0.315,"c2":0.27,"c3":0.757},{"time":0.5}]},"Scatter_B_9_Cap2":{"scale":[{"time":0.0833,"curve":0.25,"c3":0.75},{"time":0.1667,"x":1.05,"y":1.05,"curve":0.307,"c3":0.642,"c4":0.35},{"time":0.25,"x":1.03,"y":1.03,"curve":0.315,"c2":0.24,"c3":0.65,"c4":0.58},{"time":0.3333,"x":1.04,"y":1.04,"curve":0.315,"c2":0.27,"c3":0.757},{"time":0.5}]}}},"Win":{"slots":{"FX4":{"color":[{"time":0.6667,"color":"ffffffff","curve":0.25,"c3":0.75},{"time":0.8333,"color":"ffffff00"}],"attachment":[{"time":0.5,"name":"FX4"}]},"Ptcl_02":{"color":[{"time":0.6667,"color":"ffe67900","curve":0.25,"c3":0.75},{"time":0.8333,"color":"ffe679ff","curve":0.25,"c3":0.75},{"time":1.0833,"color":"ffe67900"}],"attachment":[{"time":0.6667,"name":"Ptcl_02"}]},"Scatter_B_1_Text2":{"color":[{"time":0.5833,"color":"ffffff00","curve":1,"c3":0.75},{"time":0.75,"color":"ffffffff","curve":0.25,"c3":0},{"time":1,"color":"ffffff00"}],"attachment":[{"time":0.5833,"name":"Scatter_A_1-2"}]},"Scatter_B_3-2":{"color":[{"time":0.5,"color":"ffffff00","curve":0.25,"c3":0.75},{"time":0.5833,"color":"ffffffff","curve":0.25,"c3":0.75},{"time":0.75,"color":"ffffff00"}],"attachment":[{"time":0.5,"name":"Scatter_B_3-2"}]},"Scatter_B_4_Deco2":{"color":[{"time":0.5,"color":"ffffff00","curve":0.25,"c3":0.75},{"time":0.5833,"color":"ffffffff","curve":0.25,"c3":0.75},{"time":0.75,"color":"ffffff00"}],"attachment":[{"time":0.5,"name":"Scatter_B_4-2"}]},"Scatter_B_5_Frame2":{"color":[{"time":0.7333,"color":"ffffff00","curve":0.25,"c3":0.75},{"time":0.8167,"color":"ffffffff","curve":0.25,"c3":0.75},{"time":0.9,"color":"ffffff00"}],"attachment":[{"time":0.7333,"name":"Scatter_B_5-2"}]},"Scatter_B_6_Gear2":{"color":[{"time":0.7,"color":"ffffff00","curve":0.25,"c3":0.75},{"time":0.7833,"color":"ffffffff","curve":0.25,"c3":0.75},{"time":0.8667,"color":"ffffff00"}],"attachment":[{"time":0.7,"name":"Scatter_B_6-2"}]},"Scatter_B_7_Wheel2":{"color":[{"time":0.5833,"color":"ffffff00","curve":1,"c3":0.75},{"time":0.75,"color":"ffffffff","curve":0.25,"c3":0},{"time":1,"color":"ffffff00"}],"attachment":[{"time":0.5833,"name":"Scatter_B_7-2"}]},"Scatter_B_7_Wheel3":{"color":[{"time":0.5833,"color":"ffffff00","curve":1,"c3":0.75},{"time":0.75,"color":"ffffffff","curve":0.25,"c3":0},{"time":1,"color":"ffffff00"}]},"Scatter_B_8_Cap2":{"color":[{"time":0.6333,"color":"ffffff00","curve":0.25,"c3":0.75},{"time":0.7167,"color":"ffffffff","curve":0.25,"c3":0.75},{"time":0.8833,"color":"ffffff00"}],"attachment":[{"time":0.6333,"name":"Scatter_B_8-2"}]},"Scatter_B_9_Cap3":{"color":[{"time":0.5833,"color":"ffffff00","curve":0.25,"c3":0.75},{"time":0.6667,"color":"ffffffff","curve":0.25,"c3":0.75},{"time":0.8333,"color":"ffffff00"}],"attachment":[{"time":0.5833,"name":"Scatter_B_9-2"}]},"Scatter_Text_Ref":{"attachment":[{"time":0.0833,"name":"Scatter_Text_Ref_00001"},{"time":0.1667,"name":"Scatter_Text_Ref_00002"},{"time":0.25,"name":"Scatter_Text_Ref_00003"},{"time":0.3333,"name":"Scatter_Text_Ref_00004"},{"time":0.4167,"name":"Scatter_Text_Ref_00005"},{"time":0.5,"name":"Scatter_Text_Ref_00006"},{"time":0.5833,"name":"Scatter_Text_Ref_00007"},{"time":0.6667,"name":"Scatter_Text_Ref_00008"},{"time":0.75,"name":"Scatter_Text_Ref_00009"},{"time":0.8333,"name":"Scatter_Text_Ref_00010"},{"time":0.9167,"name":"Scatter_Text_Ref_00011"},{"time":1,"name":"Scatter_Text_Ref_00012"},{"time":1.0833,"name":null}]},"Spark_2":{"color":[{"time":0.75,"color":"ffffffff"},{"time":0.9167,"color":"ffffff00"}],"attachment":[{"time":0.5833,"name":"Spark_2"}]}},"bones":{"FX4":{"scale":[{"time":0.5,"x":0,"y":0,"curve":0.25,"c3":0},{"time":0.8333}]},"FX_1":{"scale":[{"time":0.6667,"x":0,"y":0,"curve":0.25,"c3":0},{"time":1.0833}]},"Scatter_B_1_Text":{"translate":[{"y":45}]},"Scatter_B_3_Pin":{"translate":[{"curve":0.25,"c3":0.75},{"time":0.5,"y":10,"curve":1,"c3":0.75},{"time":0.5833,"y":-7},{"time":0.6667,"y":3},{"time":0.75}]},"Scatter_B_4_Deco":{"scale":[{"curve":0.25,"c3":0.75},{"time":0.5,"x":1.1,"y":1.1,"curve":1,"c3":0.75},{"time":0.5833,"x":0.95,"y":0.95},{"time":0.6667,"x":1.03,"y":1.03},{"time":0.75}]},"Scatter_B_5_Frame":{"scale":[{"time":0.7333,"curve":0.25,"c3":0},{"time":0.9,"x":1.1,"y":1.1,"curve":0.25,"c3":0},{"time":1.4}]},"Scatter_B_6_Gear":{"scale":[{"time":0.7,"curve":0.25,"c3":0},{"time":0.8667,"x":1.1,"y":1.1,"curve":0.25,"c3":0},{"time":1.3667}]},"Scatter_B_7_Wheel":{"rotate":[{},{"time":0.0833,"angle":180},{"time":0.1667},{"time":0.25,"angle":-30},{"time":0.3333,"angle":15},{"time":0.4,"angle":-10},{"time":0.4667,"angle":5},{"time":0.5333,"angle":-2},{"time":0.6}],"scale":[{"time":0.5833,"curve":0.25,"c3":0},{"time":0.75,"x":1.1,"y":1.1,"curve":0.25,"c3":0},{"time":1.25}]},"Scatter_B_8_Cap1":{"scale":[{"time":0.5833,"curve":0.25,"c3":0.75},{"time":0.6667,"x":1.2,"y":1.2,"curve":0.25,"c3":0.75},{"time":0.8333}]},"Scatter_B_9_Cap2":{"scale":[{"time":0.6333,"curve":0.25,"c3":0.75},{"time":0.7167,"x":1.2,"y":1.2,"curve":0.25,"c3":0.75},{"time":0.8833}]},"Scatter_B_1_Text_Ref":{"translate":[{"y":45}]},"FX_3":{"rotate":[{"time":0.5833},{"time":0.9167,"angle":-60}],"scale":[{"time":0.5833,"x":0.2,"y":0.2,"curve":0.25,"c3":0.75},{"time":0.9167,"x":1.6,"y":1.6}]},"Scatter_B_1_Text_Actor":{"translate":[{"y":-45}],"scale":[{},{"time":0.5833,"x":0.95,"y":0.95,"curve":1,"c3":0.75},{"time":0.75,"x":1.3,"y":1.3,"curve":0.25,"c3":0},{"time":1.5}]},"Scatter_B_2_BG":{"scale":[{},{"time":0.5833,"x":0.97,"y":0.97,"curve":0.25,"c3":0},{"time":0.75,"x":1.05,"y":1.05,"curve":0.25,"c3":0},{"time":1.25}]}}}}}